{
  "last_run": 96,
  "fv_tool": "Lean 4 + Mathlib",
  "language": "C++",
  "aeneas_applicable": false,
  "targets": [
    {"name": "InterestRate", "phase": 5, "sorry_count": 3, "notes": "30 theorems, 3 Float sorry blocked on stdlib."},
    {"name": "Actual360", "phase": 5, "sorry_count": 0, "notes": "8 theorems, all proved."},
    {"name": "LinearInterpolation", "phase": 5, "sorry_count": 0, "notes": "7/7 proved."},
    {"name": "Thirty360", "phase": 5, "sorry_count": 0, "notes": "11/11 proved."},
    {"name": "NormalDistribution", "phase": 5, "sorry_count": 1, "notes": "20/21 proved. 1 sorry: HasDerivAt erf blocked."},
    {"name": "Factorial", "phase": 5, "sorry_count": 0, "notes": "10/10 proved."},
    {"name": "Bisection", "phase": 5, "sorry_count": 0, "notes": "15/15 proved."},
    {"name": "Actual365Fixed", "phase": 5, "sorry_count": 0, "notes": "8/8 proved."},
    {"name": "FloatingPointClose", "phase": 5, "sorry_count": 0, "notes": "12/12 proved."},
    {"name": "BlackFormula", "phase": 5, "sorry_count": 0, "notes": "14 theorems, Phi axiomatised."},
    {"name": "NewtonSafe", "phase": 5, "sorry_count": 0, "notes": "13/13 proved."},
    {"name": "Matrix", "phase": 5, "sorry_count": 0, "notes": "23/23 proved."},
    {"name": "PlainVanillaPayoff", "phase": 5, "sorry_count": 0, "notes": "20/20 proved."},
    {"name": "Quadratic", "phase": 5, "sorry_count": 0, "notes": "17/17 proved."},
    {"name": "Composition", "phase": 5, "sorry_count": 0, "notes": "28/28 proved."},
    {"name": "Rounding", "phase": 5, "sorry_count": 0, "notes": "20/20 proved."},
    {"name": "PrimeNumbers", "phase": 5, "sorry_count": 0, "notes": "15/15 proved."},
    {"name": "BernsteinPolynomial", "phase": 5, "sorry_count": 0, "notes": "15/15 proved."},
    {"name": "RichardsonExtrapolation", "phase": 5, "sorry_count": 0, "notes": "7/7 proved."},
    {"name": "Brent", "phase": 5, "sorry_count": 0, "notes": "14/14 proved."},
    {"name": "LagrangeInterpolation", "phase": 5, "sorry_count": 3, "notes": "6/9 proved. 3 sorry: bary_eq_classical, scaling_invariance, exact_on_linear. Complex list algebra."},
    {"name": "BinomialDistribution", "phase": 5, "sorry_count": 2, "notes": "13/15 proved. 2 sorry: pmf_sum_eq_one (binomial theorem), cdf_le_one. Run 96 created spec+proofs."},
    {"name": "Copulas", "phase": 2, "sorry_count": null, "notes": "Informal spec written run 94. Next: Lean spec."},
    {"name": "Schedule", "phase": 1, "sorry_count": null, "notes": "Identified run74. Complex, defer."}
  ],
  "open_issues": [3],
  "ci_status": "lean-ci.yml exists and healthy",
  "total_theorems": 342,
  "total_sorry": 9,
  "paper_exists": true,
  "report_updated": "2026-05-22",
  "notes": "Run 96: Added BinomialDistribution.lean (15 thms, 13 proved). Mathlib cache now downloadable. LagrangeInterpolation sorry require complex list product factoring. Next: prove pmf_sum_eq_one, Copulas spec."
}
